watcher.py
watcher-0.3.2.dist-info/METADATA
watcher-0.3.2.dist-info/WHEEL
watcher-0.3.2.dist-info/entry_points.txt
watcher-0.3.2.dist-info/top_level.txt
watcher-0.3.2.dist-info/RECORD
